publish/__init__.py
publish/greeting.py
src/publish/__init__.py
src/publish/greeting.py
test_pypi_publish_philmont-1.0.1.dist-info/METADATA
test_pypi_publish_philmont-1.0.1.dist-info/WHEEL
test_pypi_publish_philmont-1.0.1.dist-info/top_level.txt
test_pypi_publish_philmont-1.0.1.dist-info/RECORD
