Metadata-Version: 2.1
Name: test-pypi-publish-philmont
Version: 1.0.1
Summary: Just a test publishing to PyPi 
Home-page: https://bitbucket.org/pmontgomery3CI/test-pypi-publish
Author: Philip Montgomery
Author-email: pmont@cisco.com
License: MIT
Platform: UNKNOWN
Classifier: License :: OSI Approved :: MIT License
Classifier: Programming Language :: Python :: 3
Classifier: Programming Language :: Python :: 3.7
Requires-Dist: feedparser
Requires-Dist: html2text
